setup.cfg
setup.py
Meterer.egg-info/PKG-INFO
Meterer.egg-info/SOURCES.txt
Meterer.egg-info/dependency_links.txt
Meterer.egg-info/not-zip-safe
Meterer.egg-info/requires.txt
Meterer.egg-info/top_level.txt
meterer/__init__.py
meterer/client.py
meterer/s3.py