Metadata-Version: 1.1
Name: Meterer
Version: 0.3.0
Summary: Meter the user of various resources
Home-page: https://github.com/dacut/meterer
Author: David Cuthbert
Author-email: dacut@kanga.org
License: Apache
Keywords: metering,aws,s3
Platform: UNKNOWN
Classifier: Development Status :: 4 - Beta
Classifier: Intended Audience :: Developers
Classifier: License :: OSI Approved :: Apache Software License
Classifier: Programming Language :: Python
Classifier: Topic :: Software Development :: Libraries :: Python Modules
